pt_name_gen/__init__.py
pt_name_gen/first_names.csv
pt_name_gen/last_names.csv
pt_name_gen/name_match.py
pt_name_gen/pt_name_gen.py
pt_name_gen-0.3.8.dist-info/METADATA
pt_name_gen-0.3.8.dist-info/WHEEL
pt_name_gen-0.3.8.dist-info/top_level.txt
pt_name_gen-0.3.8.dist-info/RECORD
