Metadata-Version: 2.1
Name: pt-name-gen
Version: 0.3.8
Summary: A name generator in Portuguese, with support to gender classification. Um gerador de nomes em português, com suporte para classificação de gênero.
Home-page: UNKNOWN
Author: Victor Figueredo
Author-email: cto@filterfeed.com.br
License: UNKNOWN
Platform: UNKNOWN
Classifier: Development Status :: 3 - Alpha
Classifier: Intended Audience :: Developers
Classifier: License :: OSI Approved :: MIT License
Classifier: Programming Language :: Python :: 3
Classifier: Programming Language :: Python :: 3.6
Classifier: Programming Language :: Python :: 3.7
Classifier: Programming Language :: Python :: 3.8
Classifier: Programming Language :: Python :: 3.9
Requires-Python: >=3.6
Requires-Dist: unidecode
